rockart/__init__.py
rockart/canvas.py
rockart/exceptions.py
rockart-0.2.3.dist-info/LICENSE
rockart-0.2.3.dist-info/METADATA
rockart-0.2.3.dist-info/WHEEL
rockart-0.2.3.dist-info/top_level.txt
rockart-0.2.3.dist-info/zip-safe
rockart-0.2.3.dist-info/RECORD
