Metadata-Version: 2.1
Name: rockart
Version: 0.2.3
Summary: A tool for drawing in terminal using Braille characters
Home-page: https://github.com/van-kalsing/rockart
Author: van-kalsing
Author-email: kalsin@inbox.ru
License: MIT
Project-URL: Bug Tracker, https://github.com/van-kalsing/rockart/issues
Project-URL: Source Code, https://github.com/van-kalsing/rockart
Keywords: pseudographics semigraphics braille terminal console
Platform: UNKNOWN
Classifier: Environment :: Console
Classifier: License :: OSI Approved :: MIT License
Classifier: Operating System :: POSIX :: Linux
Classifier: Programming Language :: Python :: 3.6
Classifier: Topic :: Terminals
Requires-Python: >=3.6.9
